fifo_mem_sync.sv
`timescale 1ns/1ps

//this module takes in enable clock and address along with the data you are trying to read and outputs any data you are trying to write. it does this by inputting or outputting the at the specified address
module fifo_mem_sync #(
    parameter DSIZE = 8,        // data width
    parameter ASIZE = 4         // address width (DEPTH = 2^ASIZE)
)(
    input  wire                 clk,     // system clock
    input  wire                 wen,     // write enable (effective/accepted)
    input  wire                 ren,     // read enable  (effective/accepted)
    input  wire [ASIZE-1:0]     waddr,   // write address
    input  wire [ASIZE-1:0]     raddr,   // read address
    input  wire [DSIZE-1:0]     wdata,   // data in
    output reg  [DSIZE-1:0]     rdata    // data out (registered)
);

    localparam DEPTH = 1 << ASIZE;

    // memory array
    reg [DSIZE-1:0] mem [0:DEPTH-1]; // storage array (each entry DSIZE bits)

    always @(posedge clk) begin
        // write first (synchronous write)
        if (wen) begin
            mem[waddr] <= wdata;
        end

        // synchronous read (data appears one cycle after ren is asserted)
        if (ren) begin
            rdata <= mem[raddr];
        end
    end

endmodule

fifo_ctrl_sync.sv
`timescale 1ns/1ps

//this module takes in the read and write enable signals and incriments the read next and write next pointers to their next slot, as well read and write pointers by setting it equal to read and write next in an alwaysblock, then outputs the address of the read and write pointers for the module before to reference

// since this is a circley fifo implementation, this means that when the read next and write next pointers are equal the fifo is either full or empty. the wrap around bit helps differentiate between the two as whenever any pointer passes the last slot in the fifo, one is added to that bit meaning that when it is empty both the wraparound and address are equal and when full only the address is equal. 
module fifo_ctrl_sync #(
    parameter ASIZE = 4   // address width (DEPTH = 2^ASIZE)
)(
    input  wire             clk,
    input  wire             rst_n,   // active-low reset
    input  wire             winc,    // write increment request (external)
    input  wire             rinc,    // read  increment request (external)
    output wire [ASIZE-1:0] waddr,   // write address for memory
    output wire [ASIZE-1:0] raddr,   // read  address for memory
    output reg              full,    // FIFO full flag (registered)
    output reg              empty,   // FIFO empty flag (registered)
    output wire             wen,     // effective write enable to memory (accepted this cycle)
    output wire             ren      // effective read  enable to memory (accepted this cycle)
);

    // one extra bit for wrap-around detection (ASIZE+1)
    reg [ASIZE:0] wptr, rptr;

    // decide whether a write or read is actually accepted this cycle ("fire")
  // Use'full' and 'empty' (viewed by external logicz) and the incoming requests winc/rinc 

//Write is allowed if FIFO not full, or if it’s full but a read is also happening (which makes room).
    wire wr_fire = winc && !(full && !rinc);

 //Read is allowed if FIFO not empty, or if it’s empty but a write is also happening (which provides data).
    wire rd_fire = rinc && !(empty && !winc);

  // next pointer values
wire [ASIZE:0] wptr_next;
wire [ASIZE:0] rptr_next;
assign wptr_next = wptr + wr_fire;  
assign rptr_next = rptr + rd_fire;

    // addresses to memory are the lower ASIZE bits of the pointers
    assign waddr = wptr[ASIZE-1:0];
    assign raddr = rptr[ASIZE-1:0];

    // NOTE: wr_fire/rd_fire are control-level signals (did the operation get accepted?).wen/ren are memory-level signals (should I toggle the memory R/W ports?). keeping them separate is good design style — in case later to adjust memory timing, add pipelining, or modify how memory sees enables (without touching the control logic)
    assign wen = wr_fire;
    assign ren = rd_fire;

    // sequential update: pointers and registered flags
    always @(posedge clk or negedge rst_n) begin
        if (!rst_n) begin
            wptr  <= 0;
            rptr  <= 0;
            full  <= 1'b0;
            empty <= 1'b1;
        end else begin
            // update pointers with accepted operations
            wptr <= wptr_next;
            rptr <= rptr_next;

            // compute flags from NEXT pointers (cycle-accurate)
            // full: write pointer next would match read pointer next in address bits, but top wrap bit different
            full  <= (wptr_next[ASIZE-1:0] == rptr_next[ASIZE-1:0]) &&
                     (wptr_next[ASIZE]     != rptr_next[ASIZE]);

            // empty: next pointers equal (no data)
            empty <= (wptr_next == rptr_next);
        end
    end

endmodule

design.sv
`include "fifo_ctrl_sync.sv"
`include "fifo_mem_sync.sv"

`timescale 1ns/1ps

// this module is the top-level FIFO wrapper that instantiates two other modules: ctrl + mem
module fifo_sync #(
    parameter DSIZE = 8,
    parameter ASIZE = 4
)(
    input  wire                 clk,
    input  wire                 rst_n,   // active-low reset
    input  wire                 winc,    // write request (external)
    input  wire                 rinc,    // read  request (external)
    input  wire [DSIZE-1:0]     wdata,   // write data (external)
    output wire [DSIZE-1:0]     rdata,   // read  data (external)
    output wire                 wfull,   // FIFO full (external)
    output wire                 rempty   // FIFO empty (external)
);

    // internal wires between ctrl and mem
    wire [ASIZE-1:0] waddr;
    wire [ASIZE-1:0] raddr;
    wire wen_eff;
    wire ren_eff;
    wire full_reg;
    wire empty_reg;

    // Instantiate control module
    fifo_ctrl_sync #(.ASIZE(ASIZE)) ctrl (
        .clk   (clk),
        .rst_n (rst_n),
        .winc  (winc),
        .rinc  (rinc),
        .waddr (waddr),
        .raddr (raddr),
        .full  (full_reg),
        .empty (empty_reg),
        .wen   (wen_eff),
        .ren   (ren_eff)
    );

    // Instantiate memory module
    fifo_mem_sync #(.DSIZE(DSIZE), .ASIZE(ASIZE)) mem (
        .clk  (clk),
        .wen  (wen_eff),
        .ren  (ren_eff),
        .waddr(waddr),
        .raddr(raddr),
        .wdata(wdata),
        .rdata(rdata)
    );

    // map internal flags to top-level outputs (names expected by testbench)
    assign wfull  = full_reg;
    assign rempty = empty_reg;

endmodule

testbench.sv
`timescale 1ns/1ps
//golden model self checking testbench

module fifo_sync_tb;
  parameter DSIZE = 8;
  parameter ASIZE = 4; // depth = 16 (4^2)
  parameter DEPTH  = (1 << ASIZE); //depth = 2^ASIZE

  // Testbench signals
  reg clk, rst_n;
  reg winc, rinc;
  reg [DSIZE-1:0] wdata;
  wire [DSIZE-1:0] rdata;
  wire wfull, rempty;

  // golden reference model (software FIFO)
  //software FIFO implemented as an array + two pointers + an occupancy count. essentially “another FIFO,” but purely behavioral, used to compute the expected behavior
  
  reg [DSIZE-1:0] golden_mem [0:DEPTH-1]; //array with size depth thcan hold size per slot
  integer write_ptr, read_ptr, count; //full when count == DEPTH

  // FIFO instantiation
  fifo_sync #(.DSIZE(DSIZE), .ASIZE(ASIZE)) dut (
    .clk(clk), //On the left is port name in  DUT.On the right is signal in testbench.
    .rst_n(rst_n),
    .winc(winc),
    .rinc(rinc),
    .wdata(wdata),
    .rdata(rdata),
    .wfull(wfull),
    .rempty(rempty)
  );

  // Clock 
  always #5 clk = ~clk;

  // initialize signals
  initial begin
    $dumpfile("dump.vcd");
    $dumpvars(0, fifo_sync_tb);

    clk = 0;
    rst_n = 0;
    winc = 0;
    rinc = 0;
    wdata = 0;
    write_ptr = 0;
    read_ptr = 0;
    count = 0;

    #20 rst_n = 1; // release reset, #20 (with a 10 ns clock period) gives ~2 cycles of clean reset

    // Run test cases
    test_fifo();

    #200 $finish;
  end

  // Golden reference tasks
  task golden_write(input [DSIZE-1:0] data);
    begin
      if (count < DEPTH) begin
        golden_mem[write_ptr] = data;
        write_ptr = (write_ptr + 1) % DEPTH; //since we are mimicing a circley fifo implmentaion, % DEPTH allows the pointer to wrap back to the beginning (eg. depth 4 after index 3 would go back to 0)
        count = count + 1;
      end
    end
  endtask

  task golden_read(output [DSIZE-1:0] data);
    begin
      if (count > 0) begin
        data = golden_mem[read_ptr];
        read_ptr = (read_ptr + 1) % DEPTH; 
        count = count - 1;
      end
      // if empty, 'data' is left unchanged 
    end
  endtask

  // test procedure
  task test_fifo;
    integer i;
    integer extra_writes, extra_reads;
    reg [DSIZE-1:0] expected;
    reg [DSIZE-1:0] last_rdata;
    begin
      $display("Starting FIFO test...");

      // 1) write 10 values
      
      for (i = 0; i < 10; i = i + 1) begin
        @(negedge clk);  //The TB sets requests at negedge so they are stable for the DUT sampling on posedge
        if (!wfull) begin
          wdata = ($random & 8'hFF); //$random returns a 32-bit value; mask to 8 bits to match DSIZE
          winc = 1;
          golden_write(wdata);
        end
        @(negedge clk) winc = 0;
      end

      // 2) Read 5 values 
 for (i = 0; i < 5; i = i + 1) begin
        @(negedge clk);
        if (!rempty) begin
          rinc = 1;
          golden_read(expected);
          @(posedge clk);  // DUT registers rdata here
          #1;              // sample after the DUT updated internal registers
          if (rdata !== expected) begin //!== instead of != , since checks for X or Z as wel
            $display("ERROR: Expected %0d, got %0d at time %0t", expected, rdata, $time);
          end else begin
            $display("PASS: Read %0d correctly at time %0t", rdata, $time);
          end
        end
        @(negedge clk) rinc = 0;
      end

      // 3) Fill until full

      while (!wfull) begin
        @(negedge clk);
        wdata = ($random & 8'hFF);
        winc = 1;
        golden_write(wdata);
        @(negedge clk) winc = 0;
      end
      $display("FIFO is full at time %0t (golden count = %0d)", $time, count);

      // 4) overflow: try extra writes
 
      extra_writes = 3;
      for (i = 0; i < extra_writes; i = i + 1) begin
        @(negedge clk);
        wdata = ($random & 8'hFF);
        winc = 1;            // attempt write regardless of wfull
        @(negedge clk) winc = 0;
      end
      $display("Attempted %0d extra writes at time %0t (golden count should still be %0d)", extra_writes, $time, count);

      // 5) Drain FIFO to verify matches golden model 
  
      while (!rempty) begin
        @(negedge clk);
        rinc = 1;
        golden_read(expected);
        @(posedge clk); #1;
        if (rdata !== expected) begin
          $display("ERROR: Expected %0d, got %0d at time %0t", expected, rdata, $time);
        end else begin
          $display("PASS: Read %0d correctly at time %0t", rdata, $time);
        end
        @(negedge clk) rinc = 0;
      end
      $display("FIFO drained; golden count = %0d; DUT rempty=%0b at time %0t", count, rempty, $time);


      // 6) underflow: try to read when empty
      // ensure rempty stays asserted
      // ensure rdata does not change by comparing to capture last_rdata
      // capture last_rdata (stable at negedge)
      @(negedge clk);
      last_rdata = rdata;

      extra_reads = 3;
      for (i = 0; i < extra_reads; i = i + 1) begin
        @(negedge clk);
        rinc = 1;
        @(posedge clk); #1;     
        if (!rempty) begin
          $display("ERROR: Underflow - rempty deasserted during extra read attempt at time %0t", $time);
        end
        if (rdata !== last_rdata) begin
          $display("ERROR: Underflow - rdata changed unexpectedly (was %0d now %0d) at time %0t", last_rdata, rdata, $time);
        end else begin
          $display("PASS: Underflow attempt %0d did not change rdata/rempty at time %0t", i, $time);
        end
        @(negedge clk) rinc = 0;
      end
      $display("Underflow attempts completed; golden count = %0d at time %0t", count, $time);

      
      // 7) Sanity check
      @(negedge clk);
      wdata = 8'hA5;
      winc = 1;
      golden_write(wdata);
      @(negedge clk) winc = 0;

      @(negedge clk);
      if (!rempty) begin
        rinc = 1;
        golden_read(expected);
        @(posedge clk); #1;
        if (rdata !== expected) begin
          $display("ERROR: Sanity check failed. Expected %0d, got %0d at %0t", expected, rdata, $time);
        end else begin
          $display("PASS: Sanity write/read OK (%0d) at %0t", rdata, $time);
        end
        @(negedge clk) rinc = 0;
      end else begin
        $display("ERROR: Sanity check - FIFO unexpectedly empty at time %0t", $time);
      end

      $display("All tests complete.");
    end
  endtask

endmodule

dump.vcd
$date
	Mon Sep  1 16:11:24 2025
$end
$version
	Icarus Verilog
$end
$timescale
	1ps
$end
$scope module fifo_sync_tb $end
$var wire 1 ! wfull $end
$var wire 1 " rempty $end
$var wire 8 # rdata [7:0] $end
$var parameter 32 $ ASIZE $end
$var parameter 36 % DEPTH $end
$var parameter 32 & DSIZE $end
$var reg 1 ' clk $end
$var reg 1 ( rinc $end
$var reg 1 ) rst_n $end
$var reg 8 * wdata [7:0] $end
$var reg 1 + winc $end
$var integer 32 , count [31:0] $end
$var integer 32 - read_ptr [31:0] $end
$var integer 32 . write_ptr [31:0] $end
$scope module dut $end
$var wire 1 ' clk $end
$var wire 1 " rempty $end
$var wire 1 ( rinc $end
$var wire 1 ) rst_n $end
$var wire 8 / wdata [7:0] $end
$var wire 1 ! wfull $end
$var wire 1 + winc $end
$var wire 1 0 wen_eff $end
$var wire 4 1 waddr [3:0] $end
$var wire 1 2 ren_eff $end
$var wire 8 3 rdata [7:0] $end
$var wire 4 4 raddr [3:0] $end
$var wire 1 5 full_reg $end
$var wire 1 6 empty_reg $end
$var parameter 32 7 ASIZE $end
$var parameter 32 8 DSIZE $end
$scope module ctrl $end
$var wire 1 ' clk $end
$var wire 1 9 rd_fire $end
$var wire 1 2 ren $end
$var wire 1 ( rinc $end
$var wire 1 ) rst_n $end
$var wire 1 0 wen $end
$var wire 1 + winc $end
$var wire 1 : wr_fire $end
$var wire 5 ; wptr_next [4:0] $end
$var wire 4 < waddr [3:0] $end
$var wire 5 = rptr_next [4:0] $end
$var wire 4 > raddr [3:0] $end
$var parameter 32 ? ASIZE $end
$var reg 1 6 empty $end
$var reg 1 5 full $end
$var reg 5 @ rptr [4:0] $end
$var reg 5 A wptr [4:0] $end
$upscope $end
$scope module mem $end
$var wire 1 ' clk $end
$var wire 4 B raddr [3:0] $end
$var wire 1 2 ren $end
$var wire 4 C waddr [3:0] $end
$var wire 8 D wdata [7:0] $end
$var wire 1 0 wen $end
$var parameter 32 E ASIZE $end
$var parameter 36 F DEPTH $end
$var parameter 32 G DSIZE $end
$var reg 8 H rdata [7:0] $end
$upscope $end
$upscope $end
$scope task golden_read $end
$var reg 8 I data [7:0] $end
$upscope $end
$scope task golden_write $end
$var reg 8 J data [7:0] $end
$upscope $end
$scope task test_fifo $end
$var reg 8 K expected [7:0] $end
$var reg 8 L last_rdata [7:0] $end
$var integer 32 M extra_reads [31:0] $end
$var integer 32 N extra_writes [31:0] $end
$var integer 32 O i [31:0] $end
$upscope $end
$upscope $end
$enddefinitions $end
$comment Show the parameter values. $end
$dumpall
b1000 G
b10000 F
b100 E
b100 ?
b1000 8
b100 7
b1000 &
b10000 %
b100 $
$end
#0
$dumpvars
bx O
bx N
bx M
bx L
bx K
bx J
bx I
bx H
b0 D
b0 C
b0 B
b0 A
b0 @
b0 >
b0 =
b0 <
b0 ;
0:
09
16
05
b0 4
bx 3
02
b0 1
00
b0 /
b0 .
b0 -
b0 ,
0+
b0 *
0)
0(
0'
bx #
1"
0!
$end
#5000
1'
#10000
0'
#15000
1'
#20000
10
b1 ;
1:
b1 ,
b1 .
b100100 J
1+
b100100 *
b100100 /
b100100 D
0'
b0 O
1)
#25000
b1 1
b1 <
b1 C
0"
06
b10 ;
b1 A
1'
#30000
00
b1 ;
0:
b1 O
0+
0'
#35000
1'
#40000
10
b10 ;
1:
b10 ,
b10 .
b10000001 J
1+
b10000001 *
b10000001 /
b10000001 D
0'
#45000
b10 1
b10 <
b10 C
b11 ;
b10 A
1'
#50000
00
b10 ;
0:
b10 O
0+
0'
#55000
1'
#60000
10
b11 ;
1:
b11 ,
b11 .
b1001 J
1+
b1001 *
b1001 /
b1001 D
0'
#65000
b11 1
b11 <
b11 C
b100 ;
b11 A
1'
#70000
00
b11 ;
0:
b11 O
0+
0'
#75000
1'
#80000
10
b100 ;
1:
b100 ,
b100 .
b1100011 J
1+
b1100011 *
b1100011 /
b1100011 D
0'
#85000
b100 1
b100 <
b100 C
b101 ;
b100 A
1'
#90000
00
b100 ;
0:
b100 O
0+
0'
#95000
1'
#100000
10
b101 ;
1:
b101 ,
b101 .
b1101 J
1+
b1101 *
b1101 /
b1101 D
0'
#105000
b101 1
b101 <
b101 C
b110 ;
b101 A
1'
#110000
00
b101 ;
0:
b101 O
0+
0'
#115000
1'
#120000
10
b110 ;
1:
b110 ,
b110 .
b10001101 J
1+
b10001101 *
b10001101 /
b10001101 D
0'
#125000
b110 1
b110 <
b110 C
b111 ;
b110 A
1'
#130000
00
b110 ;
0:
b110 O
0+
0'
#135000
1'
#140000
10
b111 ;
1:
b111 ,
b111 .
b1100101 J
1+
b1100101 *
b1100101 /
b1100101 D
0'
#145000
b111 1
b111 <
b111 C
b1000 ;
b111 A
1'
#150000
00
b111 ;
0:
b111 O
0+
0'
#155000
1'
#160000
10
b1000 ;
1:
b1000 ,
b1000 .
b10010 J
1+
b10010 *
b10010 /
b10010 D
0'
#165000
b1000 1
b1000 <
b1000 C
b1001 ;
b1000 A
1'
#170000
00
b1000 ;
0:
b1000 O
0+
0'
#175000
1'
#180000
10
b1001 ;
1:
b1001 ,
b1001 .
b1 J
1+
b1 *
b1 /
b1 D
0'
#185000
b1001 1
b1001 <
b1001 C
b1010 ;
b1001 A
1'
#190000
00
b1001 ;
0:
b1001 O
0+
0'
#195000
1'
#200000
10
b1010 ;
1:
b1010 ,
b1010 .
b1101 J
1+
b1101 *
b1101 /
b1101 D
0'
#205000
b1010 1
b1010 <
b1010 C
b1011 ;
b1010 A
1'
#210000
00
b1010 ;
0:
b0 O
0+
0'
#215000
1'
#220000
12
b1 =
19
b100100 K
b1001 ,
b1 -
b100100 I
1(
0'
#225000
b1 4
b1 >
b1 B
b10 =
b1 @
b100100 #
b100100 3
b100100 H
1'
#230000
02
b1 =
09
b1 O
0(
0'
#235000
1'
#240000
12
b10 =
19
b10000001 K
b1000 ,
b10 -
b10000001 I
1(
0'
#245000
b10 4
b10 >
b10 B
b11 =
b10 @
b10000001 #
b10000001 3
b10000001 H
1'
#250000
02
b10 =
09
b10 O
0(
0'
#255000
1'
#260000
12
b11 =
19
b1001 K
b111 ,
b11 -
b1001 I
1(
0'
#265000
b11 4
b11 >
b11 B
b100 =
b11 @
b1001 #
b1001 3
b1001 H
1'
#270000
02
b11 =
09
b11 O
0(
0'
#275000
1'
#280000
12
b100 =
19
b1100011 K
b110 ,
b100 -
b1100011 I
1(
0'
#285000
b100 4
b100 >
b100 B
b101 =
b100 @
b1100011 #
b1100011 3
b1100011 H
1'
#290000
02
b100 =
09
b100 O
0(
0'
#295000
1'
#300000
12
b101 =
19
b1101 K
b101 ,
b101 -
b1101 I
1(
0'
#305000
b101 4
b101 >
b101 B
b110 =
b101 @
b1101 #
b1101 3
b1101 H
1'
#310000
02
b101 =
09
b101 O
0(
0'
#315000
1'
#320000
10
b1011 ;
1:
b110 ,
b1011 .
b1110110 J
1+
b1110110 *
b1110110 /
b1110110 D
0'
#325000
b1011 1
b1011 <
b1011 C
b1100 ;
b1011 A
1'
#330000
00
b1011 ;
0:
0+
0'
#335000
1'
#340000
10
b1100 ;
1:
b111 ,
b1100 .
b111101 J
1+
b111101 *
b111101 /
b111101 D
0'
#345000
b1100 1
b1100 <
b1100 C
b1101 ;
b1100 A
1'
#350000
00
b1100 ;
0:
0+
0'
#355000
1'
#360000
10
b1101 ;
1:
b1000 ,
b1101 .
b11101101 J
1+
b11101101 *
b11101101 /
b11101101 D
0'
#365000
b1101 1
b1101 <
b1101 C
b1110 ;
b1101 A
1'
#370000
00
b1101 ;
0:
0+
0'
#375000
1'
#380000
10
b1110 ;
1:
b1001 ,
b1110 .
b10001100 J
1+
b10001100 *
b10001100 /
b10001100 D
0'
#385000
b1110 1
b1110 <
b1110 C
b1111 ;
b1110 A
1'
#390000
00
b1110 ;
0:
0+
0'
#395000
1'
#400000
10
b1111 ;
1:
b1010 ,
b1111 .
b11111001 J
1+
b11111001 *
b11111001 /
b11111001 D
0'
#405000
b1111 1
b1111 <
b1111 C
b10000 ;
b1111 A
1'
#410000
00
b1111 ;
0:
0+
0'
#415000
1'
#420000
10
b10000 ;
1:
b1011 ,
b0 .
b11000110 J
1+
b11000110 *
b11000110 /
b11000110 D
0'
#425000
b0 1
b0 <
b0 C
b10001 ;
b10000 A
1'
#430000
00
b10000 ;
0:
0+
0'
#435000
1'
#440000
10
b10001 ;
1:
b1100 ,
b1 .
b11000101 J
1+
b11000101 *
b11000101 /
b11000101 D
0'
#445000
b1 1
b1 <
b1 C
b10010 ;
b10001 A
1'
#450000
00
b10001 ;
0:
0+
0'
#455000
1'
#460000
10
b10010 ;
1:
b1101 ,
b10 .
b10101010 J
1+
b10101010 *
b10101010 /
b10101010 D
0'
#465000
b10 1
b10 <
b10 C
b10011 ;
b10010 A
1'
#470000
00
b10010 ;
0:
0+
0'
#475000
1'
#480000
10
b10011 ;
1:
b1110 ,
b11 .
b11100101 J
1+
b11100101 *
b11100101 /
b11100101 D
0'
#485000
b11 1
b11 <
b11 C
b10100 ;
b10011 A
1'
#490000
00
b10011 ;
0:
0+
0'
#495000
1'
#500000
10
b10100 ;
1:
b1111 ,
b100 .
b1110111 J
1+
b1110111 *
b1110111 /
b1110111 D
0'
#505000
b100 1
b100 <
b100 C
b10101 ;
b10100 A
1'
#510000
00
b10100 ;
0:
0+
0'
#515000
1'
#520000
10
b10101 ;
1:
b10000 ,
b101 .
b10010 J
1+
b10010 *
b10010 /
b10010 D
0'
#525000
00
0:
b101 1
b101 <
b101 C
1!
15
b10101 ;
b10101 A
1'
#530000
b0 O
b11 N
0+
0'
#535000
1'
#540000
1+
b10001111 *
b10001111 /
b10001111 D
0'
#545000
1'
#550000
b1 O
0+
0'
#555000
1'
#560000
1+
b11110010 *
b11110010 /
b11110010 D
0'
#565000
1'
#570000
b10 O
0+
0'
#575000
1'
#580000
1+
b11001110 *
b11001110 /
b11001110 D
0'
#585000
1'
#590000
b11 O
0+
0'
#595000
1'
#600000
12
b110 =
19
b10001101 K
b1111 ,
b110 -
b10001101 I
1(
0'
#605000
b110 4
b110 >
b110 B
0!
05
b111 =
b110 @
b10001101 #
b10001101 3
b10001101 H
1'
#610000
02
b110 =
09
0(
0'
#615000
1'
#620000
12
b111 =
19
b1100101 K
b1110 ,
b111 -
b1100101 I
1(
0'
#625000
b111 4
b111 >
b111 B
b1000 =
b111 @
b1100101 #
b1100101 3
b1100101 H
1'
#630000
02
b111 =
09
0(
0'
#635000
1'
#640000
12
b1000 =
19
b10010 K
b1101 ,
b1000 -
b10010 I
1(
0'
#645000
b1000 4
b1000 >
b1000 B
b1001 =
b1000 @
b10010 #
b10010 3
b10010 H
1'
#650000
02
b1000 =
09
0(
0'
#655000
1'
#660000
12
b1001 =
19
b1 K
b1100 ,
b1001 -
b1 I
1(
0'
#665000
b1001 4
b1001 >
b1001 B
b1010 =
b1001 @
b1 #
b1 3
b1 H
1'
#670000
02
b1001 =
09
0(
0'
#675000
1'
#680000
12
b1010 =
19
b1101 K
b1011 ,
b1010 -
b1101 I
1(
0'
#685000
b1010 4
b1010 >
b1010 B
b1011 =
b1010 @
b1101 #
b1101 3
b1101 H
1'
#690000
02
b1010 =
09
0(
0'
#695000
1'
#700000
12
b1011 =
19
b1110110 K
b1010 ,
b1011 -
b1110110 I
1(
0'
#705000
b1011 4
b1011 >
b1011 B
b1100 =
b1011 @
b1110110 #
b1110110 3
b1110110 H
1'
#710000
02
b1011 =
09
0(
0'
#715000
1'
#720000
12
b1100 =
19
b111101 K
b1001 ,
b1100 -
b111101 I
1(
0'
#725000
b1100 4
b1100 >
b1100 B
b1101 =
b1100 @
b111101 #
b111101 3
b111101 H
1'
#730000
02
b1100 =
09
0(
0'
#735000
1'
#740000
12
b1101 =
19
b11101101 K
b1000 ,
b1101 -
b11101101 I
1(
0'
#745000
b1101 4
b1101 >
b1101 B
b1110 =
b1101 @
b11101101 #
b11101101 3
b11101101 H
1'
#750000
02
b1101 =
09
0(
0'
#755000
1'
#760000
12
b1110 =
19
b10001100 K
b111 ,
b1110 -
b10001100 I
1(
0'
#765000
b1110 4
b1110 >
b1110 B
b1111 =
b1110 @
b10001100 #
b10001100 3
b10001100 H
1'
#770000
02
b1110 =
09
0(
0'
#775000
1'
#780000
12
b1111 =
19
b11111001 K
b110 ,
b1111 -
b11111001 I
1(
0'
#785000
b1111 4
b1111 >
b1111 B
b10000 =
b1111 @
b11111001 #
b11111001 3
b11111001 H
1'
#790000
02
b1111 =
09
0(
0'
#795000
1'
#800000
12
b10000 =
19
b11000110 K
b101 ,
b0 -
b11000110 I
1(
0'
#805000
b0 4
b0 >
b0 B
b10001 =
b10000 @
b11000110 #
b11000110 3
b11000110 H
1'
#810000
02
b10000 =
09
0(
0'
#815000
1'
#820000
12
b10001 =
19
b11000101 K
b100 ,
b1 -
b11000101 I
1(
0'
#825000
b1 4
b1 >
b1 B
b10010 =
b10001 @
b11000101 #
b11000101 3
b11000101 H
1'
#830000
02
b10001 =
09
0(
0'
#835000
1'
#840000
12
b10010 =
19
b10101010 K
b11 ,
b10 -
b10101010 I
1(
0'
#845000
b10 4
b10 >
b10 B
b10011 =
b10010 @
b10101010 #
b10101010 3
b10101010 H
1'
#850000
02
b10010 =
09
0(
0'
#855000
1'
#860000
12
b10011 =
19
b11100101 K
b10 ,
b11 -
b11100101 I
1(
0'
#865000
b11 4
b11 >
b11 B
b10100 =
b10011 @
b11100101 #
b11100101 3
b11100101 H
1'
#870000
02
b10011 =
09
0(
0'
#875000
1'
#880000
12
b10100 =
19
b1110111 K
b1 ,
b100 -
b1110111 I
1(
0'
#885000
b100 4
b100 >
b100 B
b10101 =
b10100 @
b1110111 #
b1110111 3
b1110111 H
1'
#890000
02
b10100 =
09
0(
0'
#895000
1'
#900000
12
b10101 =
19
b10010 K
b0 ,
b101 -
b10010 I
1(
0'
#905000
02
09
b101 4
b101 >
b101 B
1"
16
b10101 =
b10101 @
b10010 #
b10010 3
b10010 H
1'
#910000
0(
0'
#915000
1'
#920000
b0 O
b11 M
b10010 L
0'
#925000
1'
#930000
1(
0'
#935000
1'
#940000
b1 O
0(
0'
#945000
1'
#950000
1(
0'
#955000
1'
#960000
b10 O
0(
0'
#965000
1'
#970000
1(
0'
#975000
1'
#980000
b11 O
0(
0'
#985000
1'
#990000
10
b10110 ;
1:
b1 ,
b110 .
b10100101 J
1+
b10100101 *
b10100101 /
b10100101 D
0'
#995000
b110 1
b110 <
b110 C
0"
06
b10111 ;
b10110 A
1'
#1000000
00
b10110 ;
0:
0+
0'
#1005000
1'
#1010000
12
b10110 =
19
b10100101 K
b0 ,
b110 -
b10100101 I
1(
0'
#1015000
02
09
b110 4
b110 >
b110 B
1"
16
b10110 =
b10110 @
b10100101 #
b10100101 3
b10100101 H
1'
#1020000
0(
0'
